setup.py
idempotent/__init__.py
idempotent/key.py
idempotent/main.py
idempotent/register.py
idempotent.egg-info/PKG-INFO
idempotent.egg-info/SOURCES.txt
idempotent.egg-info/dependency_links.txt
idempotent.egg-info/requires.txt
idempotent.egg-info/top_level.txt
idempotent.egg-info/zip-safe
scripts/idempotent