Metadata-Version: 1.1
Name: idempotent
Version: 0.0.2
Summary: Idempotence.club client
Home-page: https://idenmpotent.heroku.com
Author: Adam DePrince
Author-email: adam@pelotoncycle.com
License: Apache
Platform: UNKNOWN
Classifier: Development Status :: 3 - Alpha
Classifier: Intended Audience :: Developers
Classifier: Topic :: Software Development
Classifier: License :: OSI Approved :: Apache Software License
Classifier: Programming Language :: Python :: 2
Classifier: Programming Language :: Python :: 3
